co2mpas_dice/__init__.py
co2mpas_dice/_version.py
co2mpas_dice/crypto.py
co2mpas_dice/declaration.py
co2mpas_dice/err.py
co2mpas_dice/schema.py
co2mpas_dice/tar.py
co2mpas_dice/verify.py
co2mpas_dice-5.1.22.dist-info/LICENSE
co2mpas_dice-5.1.22.dist-info/METADATA
co2mpas_dice-5.1.22.dist-info/WHEEL
co2mpas_dice-5.1.22.dist-info/entry_points.txt
co2mpas_dice-5.1.22.dist-info/top_level.txt
co2mpas_dice-5.1.22.dist-info/RECORD
